can_py_state_machine-0.1.0.dist-info/licenses/LICENSE
can_state_machine/__init__.py
can_state_machine/can_state_machine.py
can_py_state_machine-0.1.0.dist-info/METADATA
can_py_state_machine-0.1.0.dist-info/WHEEL
can_py_state_machine-0.1.0.dist-info/top_level.txt
can_py_state_machine-0.1.0.dist-info/RECORD
