Metadata-Version: 2.4
Name: can_py_state_machine
Version: 0.1.0
Summary: A lightweight Python implementation of a generic, event-driven state machine inspired by can-state-machine.
Author-email: Eren Havuc <e.havuc@draykant.eu>
License: MIT License
Project-URL: Homepage, https://github.com/hayde/ocr-state-machine.git
Project-URL: Repository, https://github.com/hayde/ocr-state-machine.git
Keywords: state-machine,workflow,finite-state-machine
Classifier: Development Status :: 3 - Alpha
Classifier: Intended Audience :: Developers
Classifier: License :: OSI Approved :: MIT License
Classifier: Programming Language :: Python :: 3
Classifier: Topic :: Software Development :: Libraries
Requires-Python: >=3.7
License-File: LICENSE
Dynamic: license-file
